plants_sm/__init__.py
plants_sm/setup_logger.py
plants_sm/alignments/__init__.py
plants_sm/alignments/alignment.py
plants_sm/data_standardization/__init__.py
plants_sm/data_standardization/padding_enumerators.py
plants_sm/data_standardization/truncation.py
plants_sm/data_standardization/x_padder.py
plants_sm/data_standardization/compounds/__init__.py
plants_sm/data_standardization/compounds/_presets.py
plants_sm/data_standardization/compounds/deepmol_standardizers.py
plants_sm/data_standardization/compounds/padding.py
plants_sm/data_standardization/proteins/__init__.py
plants_sm/data_standardization/proteins/padding.py
plants_sm/data_standardization/proteins/standardization.py
plants_sm/data_structures/__init__.py
plants_sm/data_structures/dataset/__init__.py
plants_sm/data_structures/dataset/_utils.py
plants_sm/data_structures/dataset/dataset.py
plants_sm/data_structures/dataset/multi_input_dataset.py
plants_sm/data_structures/dataset/single_input_dataset.py
plants_sm/data_structures/dataset/batch_manager/__init__.py
plants_sm/data_structures/dataset/batch_manager/batch_manager.py
plants_sm/design_patterns/__init__.py
plants_sm/design_patterns/observer.py
plants_sm/estimation/__init__.py
plants_sm/estimation/_utils.py
plants_sm/estimation/estimator.py
plants_sm/featurization/__init__.py
plants_sm/featurization/_utils.py
plants_sm/featurization/featurizer.py
plants_sm/featurization/compounds/__init__.py
plants_sm/featurization/compounds/_presets.py
plants_sm/featurization/compounds/deepmol_descriptors.py
plants_sm/featurization/compounds/map4_fingerprint.py
plants_sm/featurization/encoding/__init__.py
plants_sm/featurization/encoding/encoder.py
plants_sm/featurization/encoding/label_encoder.py
plants_sm/featurization/encoding/one_hot_encoder.py
plants_sm/featurization/proteins/__init__.py
plants_sm/featurization/proteins/bio_embeddings/__init__.py
plants_sm/featurization/proteins/bio_embeddings/_utils.py
plants_sm/featurization/proteins/bio_embeddings/constants.py
plants_sm-0.0.3.dist-info/LICENSE
plants_sm-0.0.3.dist-info/METADATA
plants_sm-0.0.3.dist-info/WHEEL
plants_sm-0.0.3.dist-info/dependency_links.txt
plants_sm-0.0.3.dist-info/top_level.txt
plants_sm-0.0.3.dist-info/RECORD
