Metadata-Version: 2.2
Name: plants_sm
Version: 0.0.3
Summary: PlantsSM
Author: Joao Capela
License: MIT
Keywords: plants,secondary metabolism
Platform: unix
Platform: linux
Platform: osx
Platform: cygwin
Platform: win32
Classifier: Programming Language :: Python :: 3
Classifier: Programming Language :: Python :: 3 :: Only
Classifier: Programming Language :: Python :: 3.9
Classifier: Programming Language :: Python :: 3.10
Requires-Python: >=3.9
License-File: LICENSE
Requires-Dist: biopython==1.79
Requires-Dist: dask==2022.2.0
Requires-Dist: jax-unirep==2.2.0
Requires-Dist: lxml==4.9.1
Requires-Dist: matplotlib==3.5.3
Requires-Dist: modlamp==4.3.0
Requires-Dist: openpyxl==3.0.10
Requires-Dist: pandas==1.5.3
Requires-Dist: pydantic==1.10.2
Requires-Dist: PyYAML==6.0
Requires-Dist: requests==2.28.1
Requires-Dist: tqdm==4.64.1
Requires-Dist: urllib3==1.26.12
Requires-Dist: transformers==4.22.2
Requires-Dist: SmilesPE==0.0.3
Requires-Dist: fair-esm==1.0.3
Requires-Dist: cached-property==1.5.2
Requires-Dist: deepmol[preprocessing]==1.1.2
Requires-Dist: tensorflow==2.14.0
Requires-Dist: seaborn==0.12.0
Requires-Dist: tensorboard==2.14.0
Requires-Dist: fairscale==0.4.13
Requires-Dist: optuna==3.1.1
Requires-Dist: lightning==2.1.2
Provides-Extra: testing
Requires-Dist: pytest>=7.1.1; extra == "testing"
Requires-Dist: pytest-cov>=3.0.0; extra == "testing"
Requires-Dist: mypy>=0.942; extra == "testing"
Requires-Dist: flake8>=4.0.1; extra == "testing"
Requires-Dist: tox>=3.25.0; extra == "testing"
